omero_rdf_wikidata/__init__.py
omero_rdf_wikidata/idr_annotations.py
omero_rdf_wikidata-0.1.0.dist-info/LICENSE.txt
omero_rdf_wikidata-0.1.0.dist-info/METADATA
omero_rdf_wikidata-0.1.0.dist-info/WHEEL
omero_rdf_wikidata-0.1.0.dist-info/entry_points.txt
omero_rdf_wikidata-0.1.0.dist-info/top_level.txt
omero_rdf_wikidata-0.1.0.dist-info/RECORD
