Metadata-Version: 2.1
Name: omero-rdf-wikidata
Version: 0.1.0
Summary: Wikidata extension for omero-rdf
Author: The Open Microscopy Team
Project-URL: Repository, https://github.com/German-BioImaging/omero-rdf-wikidata
Project-URL: Changelog, https://github.com/German-BioImaging/omero-rdf-wikidata/blob/master/CHANGES.txt
Keywords: OMERO.cli,plugin
Classifier: Development Status :: 2 - Pre-Alpha
Classifier: Environment :: Plugins
Classifier: Intended Audience :: Developers
Classifier: Intended Audience :: End Users/Desktop
Classifier: License :: OSI Approved :: GNU General Public License v2 or later (GPLv2+)
Classifier: Natural Language :: English
Classifier: Operating System :: OS Independent
Classifier: Programming Language :: Python :: 3
Classifier: Topic :: Software Development :: Libraries :: Python Modules
Requires-Python: >3.8
License-File: LICENSE.txt
Requires-Dist: omero-rdf
Requires-Dist: wikidataintegrator
Requires-Dist: packaging
Provides-Extra: tests
Requires-Dist: pytest; extra == "tests"
Requires-Dist: restview; extra == "tests"
Requires-Dist: mox3; extra == "tests"
